{
  "danger-color": "#db0200",
  "accent-color": "#5500f2",
  "text-light-color": "#e6e6e6",
  "text-color": "#464d62",
  "secondary-text-color": "#2b3948",
  "link-color": "#4b6fd7",
  "dark-gray": "#1b1f22",
  "light-gray": "#898989",
  "extra-light-gray": "#f0f0f0",
  "success-color": "#00d70a",
  "success-notify": "#4bb133",
  "error-notify": "#b13333",
  "placeholder-color": "#dee4ed",
  "primary-gradient": "linear-gradient(to right, #006aed 0%, #3f35cb 100%)",
  "reverse-gradient": "linear-gradient(to right, #3f35cb 0%, #006aed 100%)",
  "slider-buttons-bg": "#353e4e",
  "bp-desktop-hd": "1800px",
  "bp-desktop": "1200px",
  "bp-tablets": "768px",
  "bp-phones": "480px"
}
